tfields/__init__.py
tfields/__main__.py
tfields/bases/__init__.py
tfields/bases/bases.py
tfields/bases/manifold_3.py
tfields/bounding_box.py
tfields/core.py
tfields/lib/__init__.py
tfields/lib/decorators.py
tfields/lib/grid.py
tfields/lib/io.py
tfields/lib/sets.py
tfields/lib/stats.py
tfields/lib/symbolics.py
tfields/lib/util.py
tfields/mask.py
tfields/mesh_3d.py
tfields/planes_3d.py
tfields/points_3d.py
tfields/tensor_grid.py
tfields/triangles_3d.py
tfields-0.5.0.dist-info/LICENSE.rst
tfields-0.5.0.dist-info/METADATA
tfields-0.5.0.dist-info/WHEEL
tfields-0.5.0.dist-info/RECORD
