Metadata-Version: 2.1
Name: tfields
Version: 0.5.0
Summary: Tensors, tensor fields, graphs, mesh manipulation, CAD and more on the basis of numpy.ndarrays. All objects keep track of their coordinate system. Symbolic math operations work for object manipulation.
Home-page: https://gitlab.mpcdf.mpg.de/dboe/tfields
License: MIT
Keywords: tensors, tensor-fields, graphs, mesh, numpy, math
Author: Daniel Böckenhoff
Author-email: dboe@ipp.mpg.de
Requires-Python: >=3.8,<4.0
Classifier: Development Status :: 3 - Alpha
Classifier: License :: OSI Approved :: MIT License
Classifier: Programming Language :: Python
Classifier: Programming Language :: Python :: 3
Classifier: Programming Language :: Python :: 3.8
Classifier: Programming Language :: Python :: 3.9
Classifier: Programming Language :: Python :: 3.10
Classifier: Programming Language :: Python :: 3.11
Provides-Extra: io
Requires-Dist: numpy (>=1.20.0)
Requires-Dist: numpy-stl ; extra == "io"
Requires-Dist: pathlib ; python_version < "3.10"
Requires-Dist: rna (>=0.10.0)
Requires-Dist: scipy (>=1.9.2)
Requires-Dist: sortedcontainers
Requires-Dist: sympy (<=1.6.2)
Project-URL: Documentation, https://dboe.pages.mpcdf.de/tfields
Project-URL: Repository, https://gitlab.mpcdf.mpg.de/dboe/tfields
